{
  "subtopic_id": "c8_a_quota_protests",
  "canonical_keywords": [
    "2024 Bangladesh quota reform movement",
    "Bangladesh student protests"
  ],
  "entity_keywords": [
    "Students Against Discrimination",
    "Nahid Islam",
    "Asif Mahmud",
    "Sheikh Hasina",
    "Awami League",
    "Bangladesh Chhatra League",
    "University of Dhaka",
    "Rangpur",
    "Abu Sayed",
    "razakar"
  ],
  "event_keywords": [
    "High Court quota reinstatement June 2024",
    "Hasina razakar comment July 14 2024",
    "killing of Abu Sayed in Rangpur July 16 2024",
    "Bangladesh nationwide internet shutdown",
    "Supreme Court quota ruling July 21 2024",
    "non-cooperation movement August 2024"
  ],
  "broader_context": [
    "1971 freedom fighters' descendants quota",
    "Bangladesh civil service recruitment",
    "youth unemployment in Bangladesh",
    "University of Dhaka student politics"
  ]
}